{ "compressionlevel":-1,
 "height":25,
 "infinite":false,
 "layers":[
        {
         "data":[1, 1, 1, 1, 1, 1, 1, 1, 1, 1, 1, 1, 1, 1, 1, 1, 1, 1, 1, 1, 1, 1, 1, 1, 1, 1, 1, 1, 1, 1, 1, 1, 1, 1, 1, 1, 1, 1, 1, 1,
            0, 0, 0, 0, 0, 0, 0, 0, 0, 0, 0, 0, 0, 0, 0, 0, 0, 0, 0, 0, 0, 0, 0, 0, 0, 0, 1, 0, 0, 0, 0, 0, 0, 0, 0, 0, 0, 0, 0, 1,
            0, 0, 0, 0, 0, 0, 0, 0, 0, 0, 0, 0, 0, 0, 0, 0, 0, 0, 0, 0, 0, 0, 0, 0, 0, 0, 1, 0, 0, 0, 0, 0, 0, 0, 0, 0, 0, 0, 0, 1,
            1, 1, 1, 1, 1, 1, 1, 34, 0, 0, 33, 1, 1, 1, 1, 1, 1, 1, 1, 1, 1, 1, 1, 1, 0, 0, 1, 0, 0, 1, 1, 1, 1, 1, 1, 34, 0, 0, 0, 1,
            1, 0, 0, 0, 0, 0, 0, 0, 0, 0, 1, 0, 0, 0, 0, 0, 0, 0, 0, 0, 0, 0, 0, 1, 0, 0, 1, 0, 0, 1, 0, 0, 0, 0, 0, 0, 0, 0, 0, 1,
            1, 0, 0, 0, 0, 0, 0, 0, 0, 0, 1, 0, 0, 0, 0, 0, 0, 0, 0, 0, 0, 0, 0, 1, 0, 0, 1, 0, 0, 1, 0, 0, 0, 0, 0, 0, 0, 0, 0, 1,
            1, 0, 0, 33, 1, 1, 1, 1, 1, 1, 1, 0, 0, 33, 1, 1, 1, 1, 1, 1, 1, 0, 0, 1, 0, 0, 1, 0, 0, 1, 0, 0, 33, 1, 1, 1, 1, 1, 1, 1,
            1, 0, 0, 0, 0, 0, 0, 0, 0, 0, 0, 0, 0, 0, 0, 0, 0, 0, 0, 0, 1, 0, 0, 1, 0, 0, 1, 0, 0, 1, 0, 0, 0, 0, 0, 0, 0, 0, 0, 1,
            1, 0, 0, 0, 0, 0, 0, 0, 0, 0, 0, 0, 0, 0, 0, 0, 0, 0, 0, 0, 1, 0, 0, 1, 0, 0, 1, 0, 0, 1, 0, 0, 0, 0, 0, 0, 0, 0, 0, 1,
            1, 0, 0, 33, 1, 1, 1, 1, 1, 1, 1, 1, 1, 34, 0, 0, 33, 1, 1, 1, 1, 0, 0, 1, 0, 0, 0, 0, 0, 1, 1, 1, 1, 1, 1, 1, 34, 0, 0, 1,
            1, 0, 0, 1, 0, 0, 0, 0, 0, 0, 0, 0, 0, 1, 0, 0, 0, 0, 0, 1, 0, 0, 0, 1, 0, 0, 0, 0, 0, 1, 0, 0, 0, 0, 0, 0, 0, 0, 0, 1,
            1, 0, 0, 1, 0, 0, 0, 0, 0, 0, 0, 0, 0, 1, 0, 0, 0, 0, 0, 1, 0, 0, 0, 1, 0, 0, 33, 1, 1, 1, 0, 0, 0, 0, 0, 0, 0, 0, 0, 1,
            1, 0, 0, 1, 1, 1, 1, 1, 1, 1, 34, 0, 0, 1, 1, 1, 34, 0, 0, 1, 1, 1, 1, 1, 0, 0, 1, 0, 0, 0, 0, 0, 33, 1, 1, 1, 1, 1, 1, 1,
            1, 0, 0, 0, 0, 0, 0, 0, 0, 0, 0, 0, 0, 0, 0, 0, 0, 0, 0, 0, 0, 0, 0, 0, 0, 0, 1, 0, 0, 0, 0, 0, 1, 0, 0, 0, 0, 0, 0, 1,
            1, 0, 0, 0, 0, 0, 0, 0, 0, 0, 0, 0, 0, 0, 0, 0, 0, 0, 0, 0, 0, 0, 0, 0, 0, 0, 1, 0, 0, 33, 1, 1, 1, 0, 0, 0, 0, 0, 0, 1,
            1, 1, 1, 1, 1, 1, 1, 1, 1, 1, 1, 1, 1, 1, 1, 1, 1, 1, 1, 1, 1, 1, 1, 1, 1, 1, 1, 0, 0, 1, 0, 0, 0, 0, 0, 33, 1, 1, 1, 1,
            1, 0, 0, 0, 0, 0, 1, 0, 0, 0, 0, 0, 0, 0, 0, 0, 0, 0, 0, 0, 0, 0, 0, 0, 0, 0, 0, 0, 0, 1, 0, 0, 0, 0, 0, 0, 0, 0, 0, 1,
            1, 0, 0, 0, 0, 0, 1, 0, 0, 0, 0, 0, 0, 0, 0, 0, 0, 0, 0, 0, 0, 0, 0, 0, 0, 0, 0, 0, 0, 0, 0, 0, 0, 0, 0, 0, 0, 0, 0, 1,
            1, 0, 0, 1, 0, 0, 1, 1, 1, 1, 1, 1, 1, 1, 1, 1, 1, 1, 1, 1, 1, 1, 1, 1, 1, 34, 0, 0, 0, 0, 0, 0, 33, 1, 1, 1, 34, 0, 0, 1,
            1, 0, 0, 1, 0, 0, 0, 0, 0, 0, 0, 0, 0, 0, 0, 0, 0, 0, 0, 0, 0, 0, 0, 0, 0, 0, 0, 0, 0, 0, 0, 0, 1, 0, 0, 0, 0, 0, 0, 1,
            1, 0, 0, 1, 0, 0, 0, 0, 0, 0, 0, 0, 0, 0, 0, 0, 0, 0, 0, 0, 0, 0, 0, 0, 0, 0, 0, 0, 0, 0, 0, 0, 1, 0, 0, 0, 0, 0, 0, 1,
            1, 0, 0, 1, 1, 1, 1, 1, 1, 1, 1, 1, 1, 1, 1, 1, 1, 1, 1, 1, 1, 1, 1, 1, 1, 1, 1, 1, 1, 1, 1, 1, 1, 1, 1, 1, 1, 1, 1, 1,
            1, 0, 0, 0, 0, 0, 0, 0, 0, 0, 0, 0, 0, 0, 0, 0, 0, 0, 0, 0, 0, 0, 0, 0, 0, 0, 0, 0, 0, 0, 0, 0, 0, 0, 0, 0, 0, 0, 0, 0,
            1, 0, 0, 0, 0, 0, 0, 0, 0, 0, 0, 0, 0, 0, 0, 0, 0, 0, 0, 0, 0, 0, 0, 0, 0, 0, 0, 0, 0, 0, 0, 0, 0, 0, 0, 0, 0, 0, 0, 0,
            1, 1, 1, 1, 1, 1, 1, 1, 1, 1, 1, 1, 1, 1, 1, 1, 1, 1, 1, 1, 1, 1, 1, 1, 1, 1, 1, 1, 1, 1, 1, 1, 1, 1, 1, 1, 1, 1, 1, 1],
         "height":25,
         "id":1,
         "name":"floor",
         "opacity":1,
         "type":"tilelayer",
         "visible":true,
         "width":40,
         "x":0,
         "y":0
        }, 
        {
         "data":[0, 0, 0, 0, 0, 0, 0, 0, 0, 0, 0, 0, 0, 0, 0, 0, 0, 0, 0, 0, 0, 0, 0, 0, 0, 0, 0, 0, 0, 0, 0, 0, 0, 0, 0, 0, 0, 0, 0, 0,
            0, 0, 0, 0, 0, 0, 0, 0, 0, 0, 0, 0, 0, 0, 0, 0, 0, 0, 0, 0, 0, 0, 0, 0, 0, 0, 0, 0, 0, 0, 0, 0, 0, 0, 0, 0, 0, 0, 0, 0,
            7, 7, 7, 7, 7, 7, 7, 0, 0, 0, 0, 7, 7, 7, 7, 7, 7, 7, 7, 7, 7, 7, 7, 7, 0, 0, 0, 0, 0, 7, 7, 7, 7, 7, 0, 0, 0, 0, 0, 0,
            0, 0, 0, 0, 0, 0, 0, 0, 0, 0, 0, 0, 0, 0, 0, 0, 0, 0, 0, 0, 0, 0, 0, 0, 0, 0, 0, 0, 0, 0, 0, 0, 0, 0, 0, 0, 0, 0, 0, 0,
            0, 0, 0, 0, 0, 0, 0, 0, 0, 0, 0, 0, 0, 0, 0, 0, 0, 0, 0, 0, 0, 0, 0, 0, 0, 0, 0, 0, 0, 0, 0, 0, 0, 0, 0, 0, 0, 0, 0, 0,
            0, 0, 0, 0, 7, 7, 7, 7, 7, 7, 0, 0, 0, 0, 7, 7, 7, 7, 7, 7, 7, 0, 0, 0, 0, 0, 0, 0, 0, 0, 0, 0, 0, 7, 7, 7, 7, 7, 7, 0,
            0, 0, 0, 0, 0, 0, 0, 0, 0, 0, 0, 0, 0, 0, 0, 0, 0, 0, 0, 0, 0, 0, 0, 0, 0, 0, 0, 0, 0, 0, 0, 0, 0, 0, 0, 0, 0, 0, 0, 0,
            0, 0, 0, 0, 0, 0, 0, 0, 0, 0, 0, 0, 0, 0, 0, 0, 0, 0, 0, 0, 0, 0, 0, 0, 0, 0, 0, 0, 0, 0, 0, 0, 0, 0, 0, 0, 0, 0, 0, 0,
            0, 0, 0, 0, 7, 7, 7, 7, 7, 7, 7, 7, 7, 0, 0, 0, 0, 7, 7, 7, 0, 0, 0, 0, 0, 0, 0, 0, 0, 0, 7, 7, 7, 7, 7, 7, 0, 0, 0, 0,
            0, 0, 0, 0, 0, 0, 0, 0, 0, 0, 0, 0, 0, 0, 0, 0, 0, 0, 0, 0, 0, 0, 0, 0, 0, 0, 0, 0, 0, 0, 0, 0, 0, 0, 0, 0, 0, 0, 0, 0,
            0, 0, 0, 0, 0, 0, 0, 0, 0, 0, 0, 0, 0, 0, 0, 0, 0, 0, 0, 0, 0, 0, 0, 0, 0, 0, 0, 7, 7, 0, 0, 0, 0, 0, 0, 0, 0, 0, 0, 0,
            0, 0, 0, 0, 7, 7, 7, 7, 7, 7, 0, 0, 0, 0, 7, 7, 0, 0, 0, 0, 7, 7, 7, 0, 0, 0, 0, 0, 0, 0, 0, 0, 0, 7, 7, 7, 7, 7, 7, 0,
            0, 0, 0, 0, 0, 0, 0, 0, 0, 0, 0, 0, 0, 0, 0, 0, 0, 0, 0, 0, 0, 0, 0, 0, 0, 0, 0, 0, 0, 0, 0, 0, 0, 0, 0, 0, 0, 0, 0, 0,
            0, 0, 0, 0, 0, 0, 0, 0, 0, 0, 0, 0, 0, 0, 0, 0, 0, 0, 0, 0, 0, 0, 0, 0, 0, 0, 0, 0, 0, 0, 7, 7, 0, 0, 0, 0, 0, 0, 0, 0,
            0, 7, 7, 7, 7, 7, 7, 7, 7, 7, 7, 7, 7, 7, 7, 7, 7, 7, 7, 7, 7, 7, 7, 7, 7, 7, 0, 0, 0, 0, 0, 0, 0, 0, 0, 0, 7, 7, 7, 0,
            0, 0, 0, 0, 0, 0, 0, 0, 0, 0, 0, 0, 0, 0, 0, 0, 0, 0, 0, 0, 0, 0, 0, 0, 0, 0, 0, 0, 0, 0, 0, 0, 0, 0, 0, 0, 0, 0, 0, 0,
            0, 0, 0, 0, 0, 0, 0, 0, 0, 0, 0, 0, 0, 0, 0, 0, 0, 0, 0, 0, 0, 0, 0, 0, 0, 0, 0, 0, 0, 0, 0, 0, 0, 0, 0, 0, 0, 0, 0, 0,
            0, 0, 0, 7, 0, 0, 0, 7, 7, 7, 7, 7, 7, 7, 7, 7, 7, 7, 7, 7, 7, 7, 7, 7, 7, 0, 0, 0, 0, 0, 0, 0, 0, 7, 7, 7, 0, 0, 0, 0,
            0, 0, 0, 0, 0, 0, 0, 0, 0, 0, 0, 0, 0, 0, 0, 0, 0, 0, 0, 0, 0, 0, 0, 0, 0, 0, 0, 0, 0, 0, 0, 0, 0, 0, 0, 0, 0, 0, 0, 0,
            0, 0, 0, 0, 0, 0, 0, 0, 0, 0, 0, 0, 0, 0, 0, 0, 0, 0, 0, 0, 0, 0, 0, 0, 0, 0, 0, 0, 0, 0, 0, 0, 0, 0, 0, 0, 0, 0, 0, 0,
            0, 0, 0, 0, 7, 7, 7, 7, 7, 7, 7, 7, 7, 7, 7, 7, 7, 7, 7, 7, 7, 7, 7, 7, 7, 7, 7, 7, 7, 7, 7, 7, 0, 7, 7, 7, 7, 7, 7, 0,
            0, 0, 0, 0, 0, 0, 0, 0, 0, 0, 0, 0, 0, 0, 0, 0, 0, 0, 0, 0, 0, 0, 0, 7, 0, 0, 0, 0, 0, 0, 0, 0, 0, 0, 0, 0, 0, 0, 0, 0,
            0, 0, 0, 0, 0, 0, 0, 0, 0, 0, 0, 0, 0, 0, 0, 0, 0, 0, 0, 0, 0, 0, 0, 0, 0, 0, 0, 0, 0, 0, 0, 0, 0, 0, 0, 0, 0, 0, 0, 0,
            0, 7, 7, 7, 7, 7, 7, 7, 7, 7, 7, 7, 7, 7, 7, 7, 7, 7, 7, 7, 7, 7, 7, 7, 7, 7, 7, 7, 7, 7, 7, 7, 7, 7, 7, 7, 7, 7, 7, 7,
            0, 0, 0, 0, 0, 0, 0, 0, 0, 0, 0, 0, 0, 0, 0, 0, 0, 0, 0, 0, 0, 0, 0, 0, 0, 0, 0, 0, 0, 0, 0, 0, 0, 0, 0, 0, 0, 0, 0, 0],
         "height":25,
         "id":2,
         "name":"grass",
         "opacity":1,
         "type":"tilelayer",
         "visible":true,
         "width":40,
         "x":0,
         "y":0
        }],
 "nextlayerid":4,
 "nextobjectid":1,
 "orientation":"orthogonal",
 "renderorder":"right-down",
 "tiledversion":"1.10.1",
 "tileheight":32,
 "tilesets":[
        {
         "columns":9,
         "firstgid":1,
         "image":"phaser pic\/level1taler.png",
         "imageheight":288,
         "imagewidth":288,
         "margin":0,
         "name":"map",
         "spacing":0,
         "tilecount":81,
         "tileheight":32,
         "tiles":[
                {
                 "id":0,
                 "properties":[
                        {
                         "name":"collider",
                         "type":"bool",
                         "value":true
                        }]
                }, 
                {
                 "id":1,
                 "properties":[
                        {
                         "name":"collider",
                         "type":"bool",
                         "value":true
                        }]
                }, 
                {
                 "id":2,
                 "properties":[
                        {
                         "name":"collider",
                         "type":"bool",
                         "value":true
                        }]
                }, 
                {
                 "id":3,
                 "properties":[
                        {
                         "name":"collider",
                         "type":"bool",
                         "value":true
                        }]
                }, 
                {
                 "id":4,
                 "properties":[
                        {
                         "name":"collider",
                         "type":"bool",
                         "value":true
                        }]
                }, 
                {
                 "id":5,
                 "properties":[
                        {
                         "name":"collider",
                         "type":"bool",
                         "value":true
                        }]
                }, 
                {
                 "id":6,
                 "properties":[
                        {
                         "name":"collider",
                         "type":"bool",
                         "value":true
                        }]
                }, 
                {
                 "id":7,
                 "properties":[
                        {
                         "name":"collider",
                         "type":"bool",
                         "value":true
                        }]
                }, 
                {
                 "id":8,
                 "properties":[
                        {
                         "name":"collider",
                         "type":"bool",
                         "value":true
                        }]
                }, 
                {
                 "id":9,
                 "properties":[
                        {
                         "name":"collider",
                         "type":"bool",
                         "value":true
                        }]
                }, 
                {
                 "id":10,
                 "properties":[
                        {
                         "name":"collider",
                         "type":"bool",
                         "value":true
                        }]
                }, 
                {
                 "id":11,
                 "properties":[
                        {
                         "name":"collider",
                         "type":"bool",
                         "value":true
                        }]
                }, 
                {
                 "id":12,
                 "properties":[
                        {
                         "name":"collider",
                         "type":"bool",
                         "value":true
                        }]
                }, 
                {
                 "id":13,
                 "properties":[
                        {
                         "name":"collider",
                         "type":"bool",
                         "value":true
                        }]
                }, 
                {
                 "id":14,
                 "properties":[
                        {
                         "name":"collider",
                         "type":"bool",
                         "value":true
                        }]
                }, 
                {
                 "id":15,
                 "properties":[
                        {
                         "name":"collider",
                         "type":"bool",
                         "value":true
                        }]
                }, 
                {
                 "id":16,
                 "properties":[
                        {
                         "name":"collider",
                         "type":"bool",
                         "value":true
                        }]
                }, 
                {
                 "id":17,
                 "properties":[
                        {
                         "name":"collider",
                         "type":"bool",
                         "value":true
                        }]
                }, 
                {
                 "id":18,
                 "properties":[
                        {
                         "name":"collider",
                         "type":"bool",
                         "value":true
                        }]
                }, 
                {
                 "id":19,
                 "properties":[
                        {
                         "name":"collider",
                         "type":"bool",
                         "value":true
                        }]
                }, 
                {
                 "id":20,
                 "properties":[
                        {
                         "name":"collider",
                         "type":"bool",
                         "value":true
                        }]
                }, 
                {
                 "id":21,
                 "properties":[
                        {
                         "name":"collider",
                         "type":"bool",
                         "value":true
                        }]
                }, 
                {
                 "id":22,
                 "properties":[
                        {
                         "name":"collider",
                         "type":"bool",
                         "value":true
                        }]
                }, 
                {
                 "id":23,
                 "properties":[
                        {
                         "name":"collider",
                         "type":"bool",
                         "value":true
                        }]
                }, 
                {
                 "id":24,
                 "properties":[
                        {
                         "name":"collider",
                         "type":"bool",
                         "value":true
                        }]
                }, 
                {
                 "id":25,
                 "properties":[
                        {
                         "name":"collider",
                         "type":"bool",
                         "value":true
                        }]
                }, 
                {
                 "id":26,
                 "properties":[
                        {
                         "name":"collider",
                         "type":"bool",
                         "value":true
                        }]
                }, 
                {
                 "id":27,
                 "properties":[
                        {
                         "name":"collider",
                         "type":"bool",
                         "value":true
                        }]
                }, 
                {
                 "id":28,
                 "properties":[
                        {
                         "name":"collider",
                         "type":"bool",
                         "value":true
                        }]
                }, 
                {
                 "id":29,
                 "properties":[
                        {
                         "name":"collider",
                         "type":"bool",
                         "value":true
                        }]
                }, 
                {
                 "id":30,
                 "properties":[
                        {
                         "name":"collider",
                         "type":"bool",
                         "value":true
                        }]
                }, 
                {
                 "id":31,
                 "properties":[
                        {
                         "name":"collider",
                         "type":"bool",
                         "value":true
                        }]
                }, 
                {
                 "id":32,
                 "properties":[
                        {
                         "name":"collider",
                         "type":"bool",
                         "value":true
                        }]
                }, 
                {
                 "id":33,
                 "properties":[
                        {
                         "name":"collider",
                         "type":"bool",
                         "value":true
                        }]
                }, 
                {
                 "id":34,
                 "properties":[
                        {
                         "name":"collider",
                         "type":"bool",
                         "value":true
                        }]
                }, 
                {
                 "id":35,
                 "properties":[
                        {
                         "name":"collider",
                         "type":"bool",
                         "value":true
                        }]
                }, 
                {
                 "id":36,
                 "properties":[
                        {
                         "name":"collider",
                         "type":"bool",
                         "value":true
                        }]
                }, 
                {
                 "id":37,
                 "properties":[
                        {
                         "name":"collider",
                         "type":"bool",
                         "value":true
                        }]
                }, 
                {
                 "id":38,
                 "properties":[
                        {
                         "name":"collider",
                         "type":"bool",
                         "value":true
                        }]
                }, 
                {
                 "id":39,
                 "properties":[
                        {
                         "name":"collider",
                         "type":"bool",
                         "value":true
                        }]
                },
            
                {
                 "id":40,
                 "properties":[
                        {
                         "name":"collider",
                         "type":"bool",
                         "value":true
                        }]
                }, 
                {
                 "id":41,
                 "properties":[
                        {
                         "name":"collider",
                         "type":"bool",
                         "value":true
                        }]
                }, 
                {
                 "id":42,
                 "properties":[
                        {
                         "name":"collider",
                         "type":"bool",
                         "value":true
                        }]
                }, 
                {
                 "id":43,
                 "properties":[
                        {
                         "name":"collider",
                         "type":"bool",
                         "value":true
                        }]
                }, 
                {
                 "id":44,
                 "properties":[
                        {
                         "name":"collider",
                         "type":"bool",
                         "value":true
                        }]
                }, 
                {
                 "id":45,
                 "properties":[
                        {
                         "name":"collider",
                         "type":"bool",
                         "value":true
                        }]
                }, 
                {
                 "id":46,
                 "properties":[
                        {
                         "name":"collider",
                         "type":"bool",
                         "value":true
                        }]
                }, 
                {
                 "id":47,
                 "properties":[
                        {
                         "name":"collider",
                         "type":"bool",
                         "value":true
                        }]
                }, 
                {
                 "id":48,
                 "properties":[
                        {
                         "name":"collider",
                         "type":"bool",
                         "value":true
                        }]
                }, 
                {
                 "id":49,
                 "properties":[
                        {
                         "name":"collider",
                         "type":"bool",
                         "value":true
                        }]
                }, 
                {
                 "id":50,
                 "properties":[
                        {
                         "name":"collider",
                         "type":"bool",
                         "value":true
                        }]
                }, 
                {
                 "id":51,
                 "properties":[
                        {
                         "name":"collider",
                         "type":"bool",
                         "value":true
                        }]
                }, 
                {
                 "id":52,
                 "properties":[
                        {
                         "name":"collider",
                         "type":"bool",
                         "value":true
                        }]
                }, 
                {
                 "id":53,
                 "properties":[
                        {
                         "name":"collider",
                         "type":"bool",
                         "value":true
                        }]
                }, 
                {
                 "id":54,
                 "properties":[
                        {
                         "name":"collider",
                         "type":"bool",
                         "value":true
                        }]
                }, 
                {
                 "id":55,
                 "properties":[
                        {
                         "name":"collider",
                         "type":"bool",
                         "value":true
                        }]
                }, 
                {
                 "id":56,
                 "properties":[
                        {
                         "name":"collider",
                         "type":"bool",
                         "value":true
                        }]
                }, 
                {
                 "id":57,
                 "properties":[
                        {
                         "name":"collider",
                         "type":"bool",
                         "value":true
                        }]
                }, 
                {
                 "id":58,
                 "properties":[
                        {
                         "name":"collider",
                         "type":"bool",
                         "value":true
                        }]
                }, 
                {
                 "id":59,
                 "properties":[
                        {
                         "name":"collider",
                         "type":"bool",
                         "value":true
                        }]
                }, 
                {
                 "id":60,
                 "properties":[
                        {
                         "name":"collider",
                         "type":"bool",
                         "value":true
                        }]
                }, 
                {
                 "id":61,
                 "properties":[
                        {
                         "name":"collider",
                         "type":"bool",
                         "value":true
                        }]
                }, 
                {
                 "id":62,
                 "properties":[
                        {
                         "name":"collider",
                         "type":"bool",
                         "value":true
                        }]
                }, 
                {
                 "id":63,
                 "properties":[
                        {
                         "name":"collider",
                         "type":"bool",
                         "value":true
                        }]
                }, 
                {
                 "id":64,
                 "properties":[
                        {
                         "name":"collider",
                         "type":"bool",
                         "value":true
                        }]
                }, 
                {
                 "id":65,
                 "properties":[
                        {
                         "name":"collider",
                         "type":"bool",
                         "value":true
                        }]
                }, 
                {
                 "id":66,
                 "properties":[
                        {
                         "name":"collider",
                         "type":"bool",
                         "value":true
                        }]
                }, 
                {
                 "id":67,
                 "properties":[
                        {
                         "name":"collider",
                         "type":"bool",
                         "value":true
                        }]
                }, 
                {
                 "id":68,
                 "properties":[
                        {
                         "name":"collider",
                         "type":"bool",
                         "value":true
                        }]
                }, 
                {
                 "id":69,
                 "properties":[
                        {
                         "name":"collider",
                         "type":"bool",
                         "value":true
                        }]
                }, 
                {
                 "id":70,
                 "properties":[
                        {
                         "name":"collider",
                         "type":"bool",
                         "value":true
                        }]
                }, 
                {
                 "id":71,
                 "properties":[
                        {
                         "name":"collider",
                         "type":"bool",
                         "value":true
                        }]
                }, 
                {
                 "id":72,
                 "properties":[
                        {
                         "name":"collider",
                         "type":"bool",
                         "value":true
                        }]
                }, 
                {
                 "id":73,
                 "properties":[
                        {
                         "name":"collider",
                         "type":"bool",
                         "value":true
                        }]
                }, 
                {
                 "id":74,
                 "properties":[
                        {
                         "name":"collider",
                         "type":"bool",
                         "value":true
                        }]
                }, 
                {
                 "id":75,
                 "properties":[
                        {
                         "name":"collider",
                         "type":"bool",
                         "value":true
                        }]
                }, 
                {
                 "id":76,
                 "properties":[
                        {
                         "name":"collider",
                         "type":"bool",
                         "value":true
                        }]
                }, 
                {
                 "id":77,
                 "properties":[
                        {
                         "name":"collider",
                         "type":"bool",
                         "value":true
                        }]
                }, 
                {
                 "id":78,
                 "properties":[
                        {
                         "name":"collider",
                         "type":"bool",
                         "value":true
                        }]
                }, 
                {
                 "id":79,
                 "properties":[
                        {
                         "name":"collider",
                         "type":"bool",
                         "value":true
                        }]
                },
            
                {
                 "id":80,
                 "properties":[
                        {
                         "name":"collider",
                         "type":"bool",
                         "value":true
                        }]
                }],
         "tilewidth":32
        }],
 "tilewidth":32,
 "type":"map",
 "version":"1.10",
 "width":40
}